switch_model/__init__.py
switch_model/api.py
switch_model/financials.py
switch_model/main.py
switch_model/solve.py
switch_model/solve_scenarios.py
switch_model/test.py
switch_model/timescales.py
switch_model/utilities.py
switch_model/version.py
switch_model/balancing/__init__.py
switch_model/balancing/diagnose_infeasibility.py
switch_model/balancing/load_zones.py
switch_model/balancing/planning_reserves.py
switch_model/balancing/unserved_load.py
switch_model/balancing/demand_response/__init__.py
switch_model/balancing/demand_response/simple.py
switch_model/balancing/demand_response/iterative/__init__.py
switch_model/balancing/demand_response/iterative/constant_elasticity_demand_system.py
switch_model/balancing/demand_response/iterative/r_demand_system.py
switch_model/balancing/operating_reserves/__init__.py
switch_model/balancing/operating_reserves/areas.py
switch_model/balancing/operating_reserves/spinning_reserves.py
switch_model/balancing/operating_reserves/spinning_reserves_advanced.py
switch_model/energy_sources/__init__.py
switch_model/energy_sources/properties.py
switch_model/energy_sources/fuel_costs/__init__.py
switch_model/energy_sources/fuel_costs/markets.py
switch_model/energy_sources/fuel_costs/markets_expansion.py
switch_model/energy_sources/fuel_costs/simple.py
switch_model/energy_sources/fuel_costs/simple_per_timepoint.py
switch_model/energy_sources/hydrogen/__init__.py
switch_model/energy_sources/hydrogen/production.py
switch_model/generators/__init__.py
switch_model/generators/core/__init__.py
switch_model/generators/core/build.py
switch_model/generators/core/dispatch.py
switch_model/generators/core/gen_discrete_build.py
switch_model/generators/core/no_commit.py
switch_model/generators/core/commit/__init__.py
switch_model/generators/core/commit/discrete.py
switch_model/generators/core/commit/fuel_use.py
switch_model/generators/core/commit/operate.py
switch_model/generators/extensions/__init__.py
switch_model/generators/extensions/hydro_simple.py
switch_model-2.0.9.post0.dist-info/AUTHORS
switch_model-2.0.9.post0.dist-info/LICENSE
switch_model-2.0.9.post0.dist-info/LICENSE.BOILERPLATE
switch_model-2.0.9.post0.dist-info/METADATA
switch_model-2.0.9.post0.dist-info/WHEEL
switch_model-2.0.9.post0.dist-info/entry_points.txt
switch_model-2.0.9.post0.dist-info/top_level.txt
switch_model-2.0.9.post0.dist-info/RECORD
