Metadata-Version: 2.2
Name: switch_model
Version: 2.0.9.post0
Summary: Switch Power System Planning Model
Home-page: http://switch-model.org
Maintainer: Switch Authors
Maintainer-email: authors@switch-model.org
License: Apache License 2.0
Keywords: renewable,power,energy,electricity,production cost,capacity expansion,planning,optimization
Platform: any
Classifier: Development Status :: 5 - Production/Stable
Classifier: Environment :: Console
Classifier: Intended Audience :: Education
Classifier: Intended Audience :: End Users/Desktop
Classifier: Intended Audience :: Science/Research
Classifier: License :: OSI Approved :: Apache Software License
Classifier: Natural Language :: English
Classifier: Operating System :: Microsoft :: Windows
Classifier: Operating System :: MacOS :: MacOS X
Classifier: Operating System :: POSIX :: Linux
Classifier: Operating System :: Unix
Classifier: Programming Language :: Python :: 2.7
Classifier: Programming Language :: Python :: 3
Classifier: Topic :: Scientific/Engineering
Classifier: Topic :: Software Development :: Libraries :: Python Modules
Requires-Python: >=3.7.2, <3.14.0a0
License-File: LICENSE
License-File: LICENSE.BOILERPLATE
License-File: AUTHORS
Requires-Dist: Pyomo<=6.9.1,>=6.0.0
Requires-Dist: pint
Requires-Dist: testfixtures
Requires-Dist: pandas
Requires-Dist: setuptools
Provides-Extra: advanced
Requires-Dist: numpy; extra == "advanced"
Requires-Dist: scipy; extra == "advanced"
Requires-Dist: rpy2; extra == "advanced"
Requires-Dist: sympy; extra == "advanced"
Provides-Extra: dev
Requires-Dist: ipdb; extra == "dev"
Provides-Extra: plotting
Requires-Dist: plotnine; extra == "plotting"
Requires-Dist: matplotlib; extra == "plotting"
Provides-Extra: database-access
Requires-Dist: psycopg2-binary; extra == "database-access"
Dynamic: classifier
Dynamic: description
Dynamic: description-content-type
Dynamic: home-page
Dynamic: keywords
Dynamic: license
Dynamic: maintainer
Dynamic: maintainer-email
Dynamic: platform
Dynamic: provides-extra
Dynamic: requires-dist
Dynamic: requires-python
Dynamic: summary
